skilleter_modules/__init__.py
skilleter_modules/colour.py
skilleter_modules/dc_curses.py
skilleter_modules/dc_defaults.py
skilleter_modules/dc_util.py
skilleter_modules/dircolors.py
skilleter_modules/docker.py
skilleter_modules/files.py
skilleter_modules/git.py
skilleter_modules/gitlab.py
skilleter_modules/path.py
skilleter_modules/popup.py
skilleter_modules/run.py
skilleter_modules/tidy.py
skilleter_modules/venv_template.py
skilleter_modules-0.0.7.dist-info/licenses/LICENSE
skilleter_modules-0.0.7.dist-info/METADATA
skilleter_modules-0.0.7.dist-info/WHEEL
skilleter_modules-0.0.7.dist-info/top_level.txt
skilleter_modules-0.0.7.dist-info/RECORD
