Metadata-Version: 2.4
Name: skilleter_modules
Version: 0.0.7
Summary: Modules used by my various Python projects (and hopefully useful to other people)
Author-email: John Skilleter <john@skilleter.org.uk>
Project-URL: Home, https://skilleter.org.uk
Project-URL: Repository, https://gitlab.com/skilleter/skilleter-modules
Project-URL: Issues, https://gitlab.com/skilleter/skilleter-extras/-/modules
Classifier: Programming Language :: Python :: 3
Classifier: License :: OSI Approved :: GNU General Public License v3 or later (GPLv3+)
Classifier: Operating System :: OS Independent
Requires-Python: >=3.8
License-File: LICENSE
Requires-Dist: requests
Requires-Dist: pygit2
Dynamic: license-file
